pyst_client/__init__.py
pyst_client/api_client.py
pyst_client/api_response.py
pyst_client/configuration.py
pyst_client/exceptions.py
pyst_client/py.typed
pyst_client/rest.py
pyst_client-1.2.0.dist-info/licenses/LICENSE
pyst_client-1.2.0.dist-info/METADATA
pyst_client-1.2.0.dist-info/WHEEL
pyst_client-1.2.0.dist-info/top_level.txt
pyst_client-1.2.0.dist-info/RECORD
