Metadata-Version: 2.4
Name: pyst_client
Version: 1.2.0
Summary: A Python client library for the PyST (Python Semantic Taxonomy) API
Author-email: João Gonçalves <jsvgoncalves@gmail.com>
Maintainer-email: João Gonçalves <jsvgoncalves@gmail.com>
License: MIT License
Project-URL: homepage, https://github.com/cauldron/pyst-client
Project-URL: source, https://github.com/cauldron/pyst-client.git
Project-URL: tracker, https://github.com/cauldron/pyst-client/issues
Classifier: Development Status :: 5 - Production/Stable
Classifier: Intended Audience :: Developers
Classifier: License :: OSI Approved :: MIT License
Classifier: Programming Language :: Python :: 3
Classifier: Programming Language :: Python :: 3.12
Classifier: Programming Language :: Python :: 3.13
Classifier: Topic :: Scientific/Engineering
Requires-Python: >=3.12
License-File: LICENSE
Requires-Dist: aiohttp-retry>=2.8.3
Requires-Dist: aiohttp>=3.8.4
Requires-Dist: httpx
Requires-Dist: orjson
Requires-Dist: platformdirs
Requires-Dist: pydantic>=2
Requires-Dist: python-dateutil>=2.8.2
Requires-Dist: rdflib
Requires-Dist: skosify
Requires-Dist: structlog
Requires-Dist: tqdm
Requires-Dist: typing-extensions>=4.7.1
Requires-Dist: urllib3<3.0.0,>=1.25.3
Provides-Extra: dev
Requires-Dist: pytest>=7.2.1; extra == "dev"
Requires-Dist: pytest-cov>=2.8.1; extra == "dev"
Requires-Dist: tox>=3.9.0; extra == "dev"
Requires-Dist: flake8>=4.0.0; extra == "dev"
Requires-Dist: types-python-dateutil>=2.8.19.14; extra == "dev"
Requires-Dist: mypy>=1.5; extra == "dev"
Dynamic: license-file
